captcha_solve_adapter/__init__.py
captcha_solve_adapter/__main__.py
captcha_solve_adapter/solver.py
captcha_solve_adapter-1.0.dist-info/METADATA
captcha_solve_adapter-1.0.dist-info/WHEEL
captcha_solve_adapter-1.0.dist-info/top_level.txt
captcha_solve_adapter-1.0.dist-info/RECORD
