Metadata-Version: 2.1
Name: captcha-solve-adapter
Version: 1.0
Author: IMCorp
Author-email: imartemy1524@gmail.com
License: MIT
Keywords: solver,captcha,adapter,solve,AI,onnx
Classifier: Development Status :: 3 - Alpha
Classifier: Intended Audience :: Developers
Classifier: Topic :: Software Development :: Build Tools
Classifier: License :: OSI Approved :: MIT License
Classifier: Programming Language :: Python :: 3
Classifier: Programming Language :: Python :: 3.4
Classifier: Programming Language :: Python :: 3.5
Classifier: Programming Language :: Python :: 3.6
Classifier: Programming Language :: Python :: 3.7
Classifier: Programming Language :: Python :: 3.8
Classifier: Programming Language :: Python :: 3.9
Classifier: Programming Language :: Python :: 3.10
Requires-Dist: onnxruntime
Requires-Dist: numpy
Requires-Dist: opencv-python
Requires-Dist: requests
Requires-Dist: aiohttp
